py_v8n/Rule.py
py_v8n/Validator.py
py_v8n/__init__.py
py_v8n/rules.py
py_v8n-0.0.2.dist-info/METADATA
py_v8n-0.0.2.dist-info/RECORD
py_v8n-0.0.2.dist-info/WHEEL
py_v8n-0.0.2.dist-info/top_level.txt
