Metadata-Version: 2.1
Name: py-v8n
Version: 0.0.2
Summary: Python fluent validation
Home-page: https://github.com/nschejtman/py-v8n
Author: Nicolas A. Schejtman
Author-email: nschejtman93@gmail.com
License: UNKNOWN
Platform: UNKNOWN
Classifier: Programming Language :: Python :: 3
Classifier: License :: OSI Approved :: MIT License
Classifier: Operating System :: OS Independent
